predicta_app_test/__about__.py
predicta_app_test/__init__.py
predicta_app_test/main.py
predicta_app_test-0.0.1.dist-info/METADATA
predicta_app_test-0.0.1.dist-info/WHEEL
predicta_app_test-0.0.1.dist-info/RECORD
