Metadata-Version: 2.4
Name: predicta-app-test
Version: 0.0.1
Project-URL: Documentation, https://github.com/Krishanu Nayak/predicta-app-test#readme
Project-URL: Issues, https://github.com/Krishanu Nayak/predicta-app-test/issues
Project-URL: Source, https://github.com/Krishanu Nayak/predicta-app-test
Author-email: Krishanu Nayak <krishanu.nayak@riotinto.com>
License-Expression: MIT
Classifier: Development Status :: 4 - Beta
Classifier: Programming Language :: Python :: 3.12
Classifier: Programming Language :: Python :: Implementation :: CPython
Classifier: Programming Language :: Python :: Implementation :: PyPy
Requires-Python: >=3.8
Requires-Dist: pandas
